MANIFEST.in
README.md
setup.cfg
setup.py
django_invitations.egg-info/PKG-INFO
django_invitations.egg-info/SOURCES.txt
django_invitations.egg-info/dependency_links.txt
django_invitations.egg-info/not-zip-safe
django_invitations.egg-info/top_level.txt
invitations/__init__.py
invitations/adapters.py
invitations/admin.py
invitations/app_settings.py
invitations/apps.py
invitations/base_invitation.py
invitations/exceptions.py
invitations/forms.py
invitations/managers.py
invitations/models.py
invitations/signals.py
invitations/urls.py
invitations/utils.py
invitations/views.py
invitations/management/__init__.py
invitations/management/commands/__init__.py
invitations/management/commands/clear_expired_invitations.py
invitations/migrations/0001_initial.py
invitations/migrations/0002_auto_20151126_0426.py
invitations/migrations/0003_auto_20151126_1523.py
invitations/migrations/__init__.py
invitations/templates/invitations/email/email_invite_message.txt
invitations/templates/invitations/email/email_invite_subject.txt
invitations/templates/invitations/forms/_invite.html
invitations/templates/invitations/messages/invite_accepted.txt
invitations/templates/invitations/messages/invite_already_accepted.txt
invitations/templates/invitations/messages/invite_expired.txt
invitations/templates/invitations/messages/invite_invalid.txt
invitations/tests/__init__.py
tests/__init__.py
tests/conftest.py
tests/models.py
tests/allauth/__init__.py
tests/allauth/test_allauth.py
tests/basic/__init__.py
tests/basic/tests.py
tests/migrations/0001_initial.py
tests/migrations/__init__.py