Metadata-Version: 1.1
Name: django-invitations
Version: 1.9.3
Summary: Generic invitations app with support for django-allauth
Home-page: https://github.com/bee-keeper/django-invitations.git
Author: https://github.com/bee-keeper
Author-email: none@none.com
License: UNKNOWN
Download-URL: https://github.com/bee-keeper/django-invitations/tarball/1.9.3
Keywords: django,invitation,django-allauth,invite
Platform: UNKNOWN
Classifier: Development Status :: 4 - Beta
Classifier: Intended Audience :: Developers
Classifier: Topic :: Software Development :: Libraries :: Python Modules
Classifier: Environment :: Web Environment
Classifier: Topic :: Internet
Classifier: Programming Language :: Python
Classifier: Programming Language :: Python :: 3.5
Classifier: Programming Language :: Python :: 3.6
Classifier: Programming Language :: Python :: 3.7
Classifier: Programming Language :: Python :: 3.8
Classifier: Framework :: Django
